opu_analysis_lib/__init__.py
opu_analysis_lib/analysis_abundance_routine.py
opu_analysis_lib/analysis_dataset_routine.py
opu_analysis_lib/analysis_feature_score_routine.py
opu_analysis_lib/analysis_hca_routine.py
opu_analysis_lib/cli_util.py
opu_analysis_lib/cluster_metric.py
opu_analysis_lib/dim_red_visualize.py
opu_analysis_lib/feature_score.py
opu_analysis_lib/future.py
opu_analysis_lib/hca_cutoff_optimizer.py
opu_analysis_lib/normalize.py
opu_analysis_lib/opu_analysis.py
opu_analysis_lib/registry.py
opu_analysis_lib/spectra_dataset.py
opu_analysis_lib/spectra_dataset_manip.py
opu_analysis_lib/util.py
raman_opu_analysis-1.2.6.dist-info/LICENSE
raman_opu_analysis-1.2.6.dist-info/METADATA
raman_opu_analysis-1.2.6.dist-info/WHEEL
raman_opu_analysis-1.2.6.dist-info/entry_points.txt
raman_opu_analysis-1.2.6.dist-info/top_level.txt
raman_opu_analysis-1.2.6.dist-info/RECORD
