Metadata-Version: 2.1
Name: raman-opu-analysis
Version: 1.2.6
Summary: OPU anaysis for Raman single-cell spectroscopy data
Author-email: Guangyu Li <gl343@cornell.edu>
License: GNU General Public License v3
Classifier: Programming Language :: Python :: 3
Requires-Python: >=3.6
License-File: LICENSE
Requires-Dist: numpy
Requires-Dist: scipy
Requires-Dist: scikit-learn
Requires-Dist: matplotlib >=3.4.0
Requires-Dist: skfeature-gli >=1.1.1
Requires-Dist: mpllayout >=0.1.3
